promptulate/__init__.py
promptulate/agents/__init__.py
promptulate/agents/assistant_agent/__init__.py
promptulate/agents/assistant_agent/agent.py
promptulate/agents/assistant_agent/operations.py
promptulate/agents/assistant_agent/prompt.py
promptulate/agents/assistant_agent/schema.py
promptulate/agents/base.py
promptulate/agents/planner/__init__.py
promptulate/agents/planner/planner.py
promptulate/agents/planner/prompt.py
promptulate/agents/tool_agent/__init__.py
promptulate/agents/tool_agent/agent.py
promptulate/agents/tool_agent/prompt.py
promptulate/agents/web_agent/__init__.py
promptulate/agents/web_agent/agent.py
promptulate/agents/web_agent/prompt.py
promptulate/beta/__init__.py
promptulate/beta/agents/__init__.py
promptulate/beta/agents/assistant_agent/__init__.py
promptulate/beta/agents/assistant_agent/agent.py
promptulate/beta/agents/assistant_agent/operations.py
promptulate/beta/agents/assistant_agent/prompt.py
promptulate/beta/agents/assistant_agent/schema.py
promptulate/beta/agents/tool_agent/__init__.py
promptulate/beta/agents/tool_agent/agent.py
promptulate/beta/agents/tool_agent/notebook.ipynb
promptulate/beta/rag/__init__.py
promptulate/beta/st/__init__.py
promptulate/beta/st/sidebar.py
promptulate/chat.py
promptulate/client/__init__.py
promptulate/client/chat.py
promptulate/client/pne.py
promptulate/config.py
promptulate/error.py
promptulate/frameworks/__init__.py
promptulate/frameworks/conversation/__init__.py
promptulate/frameworks/conversation/conversation.py
promptulate/frameworks/prompt.py
promptulate/frameworks/schema.py
promptulate/hook/__init__.py
promptulate/hook/base.py
promptulate/hook/stdout_hook.py
promptulate/llms/__init__.py
promptulate/llms/_litellm.py
promptulate/llms/base.py
promptulate/llms/erniebot/__init__.py
promptulate/llms/erniebot/erniebot.py
promptulate/llms/erniebot/schema.py
promptulate/llms/factory.py
promptulate/llms/openai/__init__.py
promptulate/llms/openai/openai.py
promptulate/llms/openai/schema.py
promptulate-1.18.4.dist-info/LICENSE
promptulate-1.18.4.dist-info/METADATA
promptulate-1.18.4.dist-info/WHEEL
promptulate-1.18.4.dist-info/entry_points.txt
promptulate-1.18.4.dist-info/RECORD
