Metadata-Version: 2.1
Name: promptulate
Version: 1.18.4
Summary: 🚀Large language model automation and Autonomous Language Agents development framework. Build your LLM Agent Application in a pythonic way.
Home-page: https://github.com/Undertone0809/promptulate
Keywords: promptulate,pne,prompt,agent,openai,chatgpt,gpt,llm,openai,langchain,litellm
Author: Zeeland
Author-email: zeeland4work@gmail.com
Requires-Python: >=3.8.1,<4.0
Classifier: Programming Language :: Python :: 3
Classifier: Programming Language :: Python :: 3.9
Classifier: Programming Language :: Python :: 3.10
Classifier: Programming Language :: Python :: 3.11
Classifier: Programming Language :: Python :: 3.12
Requires-Dist: broadcast-service (==1.3.2)
Requires-Dist: click (>=8.1.7,<9.0.0)
Requires-Dist: cushy-storage (>=1.3.7,<2.0.0)
Requires-Dist: litellm (>=1.39.6,<2.0.0)
Requires-Dist: pydantic (>=1,<3)
Requires-Dist: python-dotenv (>=1.0.0,<2.0.0)
Requires-Dist: questionary (>=2.0.1,<3.0.0)
Requires-Dist: requests (>=2.31.0,<3.0.0)
Requires-Dist: typing-extensions (>=4.10.0,<5.0.0)
Project-URL: Repository, https://github.com/Undertone0809/promptulate
Project-URL: Source, https://github.com/Undertone0809/promptulate
